snowball/__init__.py
snowball/__main__.py
snowball/api_ref.py
snowball/constants.py
snowball/exceptions.py
snowball/snowball.py
snowball/api/__init__.py
snowball/api/capital.py
snowball/api/cube.py
snowball/api/f10.py
snowball/api/finance.py
snowball/api/live.py
snowball/api/report.py
snowball/api/user.py
snowball/utils/__init__.py
snowball/utils/token.py
moosbl-0.1.2.dist-info/LICENSE
moosbl-0.1.2.dist-info/METADATA
moosbl-0.1.2.dist-info/WHEEL
moosbl-0.1.2.dist-info/entry_points.txt
moosbl-0.1.2.dist-info/top_level.txt
moosbl-0.1.2.dist-info/RECORD
